texshade/__init__.py
texshade/texshade.py
texshade-2.0.dist-info/METADATA
texshade-2.0.dist-info/WHEEL
texshade-2.0.dist-info/top_level.txt
texshade-2.0.dist-info/zip-safe
texshade-2.0.dist-info/RECORD
