Metadata-Version: 2.1
Name: texshade
Version: 2.0
Summary: Memory-efficient implementation of texture-shading method for visualizing elevation
Home-page: https://github.com/fasiha/texshade-py
Author: Ahmed Fasih
Author-email: ahmed@aldebrn.me
License: Unlicense
Keywords: texture shading elevation terrain fractional laplacian hankel overlap save spatial frequency
Platform: UNKNOWN
Requires-Dist: array-range
Requires-Dist: nextprod
Requires-Dist: numpy
Requires-Dist: overlap-save
Requires-Dist: scipy
